cppython_git-0.1.1.dev3.dist-info/METADATA
cppython_git-0.1.1.dev3.dist-info/WHEEL
cppython_git-0.1.1.dev3.dist-info/entry_points.txt
cppython_git-0.1.1.dev3.dist-info/licenses/LICENSE.md
cppython_git/__init__.py
cppython_git/plugin.py
cppython_git/py.typed
cppython_git-0.1.1.dev3.dist-info/RECORD
